astrapia/__init__.py
astrapia/assets/__init__.py
astrapia/assets/configs/mediapipe_long.yaml
astrapia/assets/configs/mediapipe_mesh.yaml
astrapia/assets/configs/mediapipe_short.yaml
astrapia/assets/models/README.md
astrapia/assets/models/long.onnx
astrapia/assets/models/mesh.onnx
astrapia/assets/models/short.onnx
astrapia/assets/models/long.mlpackage/Manifest.json
astrapia/assets/models/long.mlpackage/Data/com.apple.CoreML/model.mlmodel
astrapia/assets/models/mesh.mlpackage/Manifest.json
astrapia/assets/models/mesh.mlpackage/Data/com.apple.CoreML/model.mlmodel
astrapia/assets/models/short.mlpackage/Manifest.json
astrapia/assets/models/short.mlpackage/Data/com.apple.CoreML/model.mlmodel
astrapia/callbacks/__init__.py
astrapia/callbacks/base.py
astrapia/callbacks/to_bchw.py
astrapia/data/__init__.py
astrapia/data/base.py
astrapia/data/detection.py
astrapia/data/face.py
astrapia/data/tensor.py
astrapia/engine/__init__.py
astrapia/engine/base.py
astrapia/engine/base_ml.py
astrapia/examples/__init__.py
astrapia/examples/mediapipe/__init__.py
astrapia/examples/mediapipe/detector.py
astrapia/examples/mediapipe/mesh.py
astrapia/geometry/__init__.py
astrapia/geometry/transform.py
astrapia/utils/__init__.py
astrapia/utils/nms_fns.py
astrapia/utils/timer.py
astrapia/utils/zipper.py
astrapia-0.2.7.dist-info/METADATA
astrapia-0.2.7.dist-info/WHEEL
astrapia-0.2.7.dist-info/entry_points.txt
astrapia-0.2.7.dist-info/licenses/LICENSE
astrapia-0.2.7.dist-info/RECORD
